pkt_kg/__init__.py
pkt_kg/__version__.py
pkt_kg/construction_approaches.py
pkt_kg/downloads.py
pkt_kg/edge_list.py
pkt_kg/kg_embedding_visualizer.py
pkt_kg/knowledge_graph.py
pkt_kg/knowledge_graph_embedder.py
pkt_kg/metadata.py
pkt_kg/owlnets.py
pkt_kg/libs/owltools
pkt_kg/utils/__init__.py
pkt_kg/utils/data_utils.py
pkt_kg/utils/kg_utils.py
pkt_kg-3.1.2.dist-info/LICENSE
pkt_kg-3.1.2.dist-info/METADATA
pkt_kg-3.1.2.dist-info/WHEEL
pkt_kg-3.1.2.dist-info/entry_points.txt
pkt_kg-3.1.2.dist-info/top_level.txt
pkt_kg-3.1.2.dist-info/RECORD
