Metadata-Version: 2.1
Name: pkt-kg
Version: 3.1.2
Summary: A Python library for scalable knowledge semantic graph construction
Home-page: https://github.com/callahantiff/PheKnowLator
Author: Tiffany J. Callahan, William A. Baumgartner, Jr.
Author-email: tiffany.callahan@cuanschutz.edu, william.baumgartner@cuanschutz.edu
License: Apache 2.0
Keywords: knowledge-graph,ontologies,formal-logic,biomedical-applications,mechanisms,translation-research,linked-open-data,owl,semantic-web,symbolic-ai,
Platform: UNKNOWN
Classifier: Development Status :: 3 - Alpha
Classifier: License :: OSI Approved :: Apache Software License
Classifier: Programming Language :: Python :: 3
Requires-Dist: argparse
Requires-Dist: click
Requires-Dist: Cython (>=0.29.14)
Requires-Dist: more-itertools
Requires-Dist: networkx
Requires-Dist: numpy (>=1.18.1)
Requires-Dist: openpyxl (>=3.0.3)
Requires-Dist: pandas (>=1.0.5)
Requires-Dist: psutil
Requires-Dist: python-json-logger
Requires-Dist: ray
Requires-Dist: rdflib
Requires-Dist: reactome2py
Requires-Dist: requests
Requires-Dist: types-requests
Requires-Dist: responses (==0.10.12)
Requires-Dist: tqdm
Requires-Dist: urllib3
Provides-Extra: test
Requires-Dist: codacy-coverage ; extra == 'test'
Requires-Dist: coveralls ; extra == 'test'
Requires-Dist: mock ; extra == 'test'
Requires-Dist: mypy ; extra == 'test'
Requires-Dist: pytest ; extra == 'test'
Requires-Dist: pytest-cov ; extra == 'test'
Requires-Dist: validate-version-code ; extra == 'test'
